interfolio_api/__init__.py
interfolio_api/interfolio_base.py
interfolio_api/interfolio_config.py
interfolio_api/interfolio_core.py
interfolio_api/interfolio_far.py
interfolio_api/interfolio_fs.py
interfolio_api/interfolio_rpt.py
interfolio_api-0.93.dist-info/METADATA
interfolio_api-0.93.dist-info/WHEEL
interfolio_api-0.93.dist-info/top_level.txt
interfolio_api-0.93.dist-info/RECORD
