Metadata-Version: 2.4
Name: interfolio_api
Version: 0.93
Summary: A Python client for Interfolio
Home-page: https://github.com/Rice-University-Academic-Affairs/Interfolio-API
Author: Rice University Office of the Vice Provost of Academic Affairs
Author-email: vpaa@rice.edu
Requires-Dist: requests
Dynamic: author
Dynamic: author-email
Dynamic: description
Dynamic: description-content-type
Dynamic: home-page
Dynamic: requires-dist
Dynamic: summary
